{"name":"Trogloditargh","imageUrls":["http://192.168.0.25:8080/images/Trogloditargh.jpg"],"description":"Los jugadores representan cavernícolas que intentan construir a base de porrazos","minPlayers":2,"maxPlayers":8,"theme":"Fantasía Medieval","complexity":"Party","location":{"id":4,"name":"Salón Izquierda Abajo"},"medium":"Tablero","style":"Maximización de puntos","victory":"Equipos","duration":45,"lastPlayedDate":null,"scoreInfo":{"scores":[{"id":24,"name":"Temática","value":0},{"id":151,"name":"Mecánicas","value":0},{"id":278,"name":"Arte","value":0},{"id":405,"name":"Originalidad","value":0}],"avgValue":0.0}}